<?xml version="1.0" encoding="UTF-8"?>
<rfi>
  <adsHeader>
    <missionId>S1A</missionId>
    <productType>SLC</productType>
    <polarisation>VH</polarisation>
    <mode>IW</mode>
    <swath>IW1</swath>
    <startTime>2023-09-16T06:37:31.485004</startTime>
    <stopTime>2023-09-16T06:37:56.645013</stopTime>
    <absoluteOrbitNumber>50349</absoluteOrbitNumber>
    <missionDataTakeId>397261</missionDataTakeId>
    <imageNumber>001</imageNumber>
  </adsHeader>
  <rfiMitigationApplied>None</rfiMitigationApplied>
  <rfiDetectionFromNoiseReportList count="12">
    <rfiDetectionFromNoiseReport>
      <swath>IW1</swath>
      <noiseSensingTime>2023-09-16T06:37:29.873191</noiseSensingTime>
      <rfiDetected>false</rfiDetected>
      <maxKLDivergence>2.751050e+00</maxKLDivergence>
      <maxFisherZ>3.320579e+00</maxFisherZ>
      <maxRfiPsd>0.000000e+00</maxRfiPsd>
    </rfiDetectionFromNoiseReport>
    <rfiDetectionFromNoiseReport>
      <swath>IW1</swath>
      <noiseSensingTime>2023-09-16T06:37:32.631477</noiseSensingTime>
      <rfiDetected>false</rfiDetected>
      <maxKLDivergence>2.572977e+00</maxKLDivergence>
      <maxFisherZ>3.268443e+00</maxFisherZ>
      <maxRfiPsd>0.000000e+00</maxRfiPsd>
    </rfiDetectionFromNoiseReport>
    <rfiDetectionFromNoiseReport>
      <swath>IW1</swath>
      <noiseSensingTime>2023-09-16T06:37:35.389747</noiseSensingTime>
      <rfiDetected>false</rfiDetected>
      <maxKLDivergence>4.387810e+00</maxKLDivergence>
      <maxFisherZ>4.302016e+00</maxFisherZ>
      <maxRfiPsd>0.000000e+00</maxRfiPsd>
    </rfiDetectionFromNoiseReport>
    <rfiDetectionFromNoiseReport>
      <swath>IW1</swath>
      <noiseSensingTime>2023-09-16T06:37:38.148033</noiseSensingTime>
      <rfiDetected>false</rfiDetected>
      <maxKLDivergence>2.904303e+00</maxKLDivergence>
      <maxFisherZ>3.478786e+00</maxFisherZ>
      <maxRfiPsd>0.000000e+00</maxRfiPsd>
    </rfiDetectionFromNoiseReport>
    <rfiDetectionFromNoiseReport>
      <swath>IW1</swath>
      <noiseSensingTime>2023-09-16T06:37:40.906303</noiseSensingTime>
      <rfiDetected>false</rfiDetected>
      <maxKLDivergence>2.334060e+00</maxKLDivergence>
      <maxFisherZ>3.119383e+00</maxFisherZ>
      <maxRfiPsd>0.000000e+00</maxRfiPsd>
    </rfiDetectionFromNoiseReport>
    <rfiDetectionFromNoiseReport>
      <swath>IW1</swath>
      <noiseSensingTime>2023-09-16T06:37:43.664588</noiseSensingTime>
      <rfiDetected>false</rfiDetected>
      <maxKLDivergence>3.535562e+00</maxKLDivergence>
      <maxFisherZ>3.933379e+00</maxFisherZ>
      <maxRfiPsd>0.000000e+00</maxRfiPsd>
    </rfiDetectionFromNoiseReport>
    <rfiDetectionFromNoiseReport>
      <swath>IW1</swath>
      <noiseSensingTime>2023-09-16T06:37:46.422859</noiseSensingTime>
      <rfiDetected>false</rfiDetected>
      <maxKLDivergence>2.937160e+00</maxKLDivergence>
      <maxFisherZ>3.568973e+00</maxFisherZ>
      <maxRfiPsd>0.000000e+00</maxRfiPsd>
    </rfiDetectionFromNoiseReport>
    <rfiDetectionFromNoiseReport>
      <swath>IW1</swath>
      <noiseSensingTime>2023-09-16T06:37:49.181144</noiseSensingTime>
      <rfiDetected>false</rfiDetected>
      <maxKLDivergence>3.560378e+00</maxKLDivergence>
      <maxFisherZ>3.725927e+00</maxFisherZ>
      <maxRfiPsd>0.000000e+00</maxRfiPsd>
    </rfiDetectionFromNoiseReport>
    <rfiDetectionFromNoiseReport>
      <swath>IW1</swath>
      <noiseSensingTime>2023-09-16T06:37:51.939414</noiseSensingTime>
      <rfiDetected>false</rfiDetected>
      <maxKLDivergence>3.737892e+00</maxKLDivergence>
      <maxFisherZ>4.045201e+00</maxFisherZ>
      <maxRfiPsd>0.000000e+00</maxRfiPsd>
    </rfiDetectionFromNoiseReport>
    <rfiDetectionFromNoiseReport>
      <swath>IW1</swath>
      <noiseSensingTime>2023-09-16T06:37:54.697685</noiseSensingTime>
      <rfiDetected>false</rfiDetected>
      <maxKLDivergence>3.668386e+00</maxKLDivergence>
      <maxFisherZ>4.004740e+00</maxFisherZ>
      <maxRfiPsd>0.000000e+00</maxRfiPsd>
    </rfiDetectionFromNoiseReport>
    <rfiDetectionFromNoiseReport>
      <swath>IW1</swath>
      <noiseSensingTime>2023-09-16T06:37:57.455970</noiseSensingTime>
      <rfiDetected>false</rfiDetected>
      <maxKLDivergence>3.295101e+00</maxKLDivergence>
      <maxFisherZ>3.769327e+00</maxFisherZ>
      <maxRfiPsd>0.000000e+00</maxRfiPsd>
    </rfiDetectionFromNoiseReport>
    <rfiDetectionFromNoiseReport>
      <swath>IW1</swath>
      <noiseSensingTime>2023-09-16T06:38:00.214256</noiseSensingTime>
      <rfiDetected>false</rfiDetected>
      <maxKLDivergence>3.230478e+00</maxKLDivergence>
      <maxFisherZ>3.710871e+00</maxFisherZ>
      <maxRfiPsd>0.000000e+00</maxRfiPsd>
    </rfiDetectionFromNoiseReport>
  </rfiDetectionFromNoiseReportList>
  <rfiBurstReportList count="11">
    <rfiBurstReport>
      <swath>IW1</swath>
      <azimuthTime>2023-09-16T06:37:28.728503</azimuthTime>
      <inBandOutBandPowerRatio>2.143806e+00</inBandOutBandPowerRatio>
    </rfiBurstReport>
    <rfiBurstReport>
      <swath>IW1</swath>
      <azimuthTime>2023-09-16T06:37:31.485004</azimuthTime>
      <inBandOutBandPowerRatio>2.342788e+00</inBandOutBandPowerRatio>
    </rfiBurstReport>
    <rfiBurstReport>
      <swath>IW1</swath>
      <azimuthTime>2023-09-16T06:37:34.247672</azimuthTime>
      <inBandOutBandPowerRatio>2.372921e+00</inBandOutBandPowerRatio>
    </rfiBurstReport>
    <rfiBurstReport>
      <swath>IW1</swath>
      <azimuthTime>2023-09-16T06:37:37.000062</azimuthTime>
      <inBandOutBandPowerRatio>2.569711e+00</inBandOutBandPowerRatio>
    </rfiBurstReport>
    <rfiBurstReport>
      <swath>IW1</swath>
      <azimuthTime>2023-09-16T06:37:39.762729</azimuthTime>
      <inBandOutBandPowerRatio>3.041867e+00</inBandOutBandPowerRatio>
    </rfiBurstReport>
    <rfiBurstReport>
      <swath>IW1</swath>
      <azimuthTime>2023-09-16T06:37:42.519230</azimuthTime>
      <inBandOutBandPowerRatio>3.721516e+00</inBandOutBandPowerRatio>
    </rfiBurstReport>
    <rfiBurstReport>
      <swath>IW1</swath>
      <azimuthTime>2023-09-16T06:37:45.275731</azimuthTime>
      <inBandOutBandPowerRatio>3.933868e+00</inBandOutBandPowerRatio>
    </rfiBurstReport>
    <rfiBurstReport>
      <swath>IW1</swath>
      <azimuthTime>2023-09-16T06:37:48.032232</azimuthTime>
      <inBandOutBandPowerRatio>3.539065e+00</inBandOutBandPowerRatio>
    </rfiBurstReport>
    <rfiBurstReport>
      <swath>IW1</swath>
      <azimuthTime>2023-09-16T06:37:50.792844</azimuthTime>
      <inBandOutBandPowerRatio>3.492971e+00</inBandOutBandPowerRatio>
    </rfiBurstReport>
    <rfiBurstReport>
      <swath>IW1</swath>
      <azimuthTime>2023-09-16T06:37:53.549345</azimuthTime>
      <inBandOutBandPowerRatio>3.674019e+00</inBandOutBandPowerRatio>
    </rfiBurstReport>
    <rfiBurstReport>
      <swath>IW1</swath>
      <azimuthTime>2023-09-16T06:37:56.309957</azimuthTime>
      <inBandOutBandPowerRatio>3.618259e+00</inBandOutBandPowerRatio>
    </rfiBurstReport>
  </rfiBurstReportList>
</rfi>
